[{"blogs_sidebar":["search-6","recentposts-4","archives-3","calendar-2","recent-posts-3"],"contact":["nav_menu-3","cs_twitter_widget-1"],"faq_sidebar":["categories-3"],"car_listing":["vehicle_search-4"],"about_us_sidebar":["nav_menu-4"],"term_and_conditions":["nav_menu-5"],"price_plan":["nav_menu-6"],"team_sidebar":["nav_menu-7"],"location_sidebar":["vehicle_search-5","text-2"],"default_page_sidebar":["categories-4","text-3"],"sidebar-1":["recent-posts-2","recent-comments-2","archives-2","meta-2"],"footer-widget-1":["categories-6","recent-posts-4","cs_social_network_widget-2","cs_mailchimp-4"]},{"search":{"6":{"title":""},"_multiwidget":1},"recentposts":{"4":{"title":"Latest News","select_category":"","showcount":"4"},"_multiwidget":1},"archives":{"3":{"title":"Blog Archives","count":1,"dropdown":0},"2":{"title":"","count":0,"dropdown":0},"_multiwidget":1},"calendar":{"2":{"title":""},"_multiwidget":1},"recent-posts":{"3":{"title":"Recent Post","number":4,"show_date":true},"2":{"title":"","number":5},"4":{"title":"Latest News","number":2,"show_date":true},"_multiwidget":1},"nav_menu":{"3":{"title":"Quick Link","nav_menu":32},"4":{"title":"Quick Links","nav_menu":32},"5":{"title":"Quick Links","nav_menu":32},"6":{"title":"Quick Links","nav_menu":32},"7":{"title":"Quick Links","nav_menu":32},"_multiwidget":1},"cs_twitter_widget":{"1":{"title":"Twitter","username":"envato","numoftweets":"3"},"_multiwidget":1},"categories":{"3":{"title":"FAQ Topics","count":0,"hierarchical":0,"dropdown":0},"4":{"title":"Categories","count":1,"hierarchical":0,"dropdown":0},"6":{"title":"Monthly Promotions","count":0,"hierarchical":0,"dropdown":0},"_multiwidget":1},"vehicle_search":{"4":{"title":""},"5":{"title":""},"_multiwidget":1},"text":{"2":{"title":"","text":"[cs_ads id=\"496505006\"]","filter":false},"3":{"title":"","text":"[cs_ads id=\"496505006\"]","filter":false},"_multiwidget":1},"recent-comments":{"2":{"title":"","number":5},"_multiwidget":1},"meta":{"2":{"title":""},"_multiwidget":1},"cs_social_network_widget":{"2":{"title":"Socail Network"},"_multiwidget":1},"cs_mailchimp":{"4":{"title":"Weekly Newsletter","description":""},"_multiwidget":1},"":{"ction":"","_multiwidget":null}}]